azure/ai/language/questionanswering/authoring/__init__.py
azure/ai/language/questionanswering/authoring/_client.py
azure/ai/language/questionanswering/authoring/_configuration.py
azure/ai/language/questionanswering/authoring/_patch.py
azure/ai/language/questionanswering/authoring/_validation.py
azure/ai/language/questionanswering/authoring/_version.py
azure/ai/language/questionanswering/authoring/py.typed
azure/ai/language/questionanswering/authoring/_operations/__init__.py
azure/ai/language/questionanswering/authoring/_operations/_operations.py
azure/ai/language/questionanswering/authoring/_operations/_patch.py
azure/ai/language/questionanswering/authoring/_utils/__init__.py
azure/ai/language/questionanswering/authoring/_utils/model_base.py
azure/ai/language/questionanswering/authoring/_utils/serialization.py
azure/ai/language/questionanswering/authoring/_utils/utils.py
azure/ai/language/questionanswering/authoring/aio/__init__.py
azure/ai/language/questionanswering/authoring/aio/_client.py
azure/ai/language/questionanswering/authoring/aio/_configuration.py
azure/ai/language/questionanswering/authoring/aio/_patch.py
azure/ai/language/questionanswering/authoring/aio/_operations/__init__.py
azure/ai/language/questionanswering/authoring/aio/_operations/_operations.py
azure/ai/language/questionanswering/authoring/aio/_operations/_patch.py
azure/ai/language/questionanswering/authoring/models/__init__.py
azure/ai/language/questionanswering/authoring/models/_enums.py
azure/ai/language/questionanswering/authoring/models/_models.py
azure/ai/language/questionanswering/authoring/models/_patch.py
azure_ai_language_questionanswering_authoring-1.0.0b1.dist-info/licenses/LICENSE
azure_ai_language_questionanswering_authoring-1.0.0b1.dist-info/METADATA
azure_ai_language_questionanswering_authoring-1.0.0b1.dist-info/WHEEL
azure_ai_language_questionanswering_authoring-1.0.0b1.dist-info/top_level.txt
azure_ai_language_questionanswering_authoring-1.0.0b1.dist-info/RECORD
